aragorn.cpython-39-darwin.so
Aragorn-0.1.dist-info/LICENSE
Aragorn-0.1.dist-info/METADATA
Aragorn-0.1.dist-info/WHEEL
Aragorn-0.1.dist-info/top_level.txt
Aragorn-0.1.dist-info/RECORD
